[ {
  "id" : "link",
  "name" : "link",
  "label" : "",
  "required" : false,
  "locked" : false,
  "supported_types" : [ "EXTERNAL", "CONTENT", "FILE", "EMAIL_ADDRESS" ],
  "show_advanced_rel_options" : false,
  "type" : "link",
  "display_width" : null,
  "default" : {
    "url" : {
      "href" : "www.hubspot.com",
      "type" : "EXTERNAL"
    },
    "no_follow" : false,
    "open_in_new_tab" : false
  }
}, {
  "id" : "button_text",
  "name" : "button_text",
  "label" : "Button text",
  "required" : true,
  "locked" : false,
  "allow_new_line" : false,
  "type" : "text",
  "display_width" : null,
  "default" : "Add a button link here"
} ]